resources/__init__.py
static_php_py/__init__.py
static_php_py/exceptions.py
static_php_py/models.py
static_php_py/php.py
static_php_py/providers.py
static_php_py-0.1.0.dist-info/METADATA
static_php_py-0.1.0.dist-info/WHEEL
static_php_py-0.1.0.dist-info/licenses/LICENSE
static_php_py-0.1.0.dist-info/RECORD
