Metadata-Version: 2.4
Name: static-php-py
Version: 0.1.0
Summary: Python wrapper library for static PHP binaries with pre-built distribution support crazywhalecc/static-php-cli
Project-URL: Homepage, https://github.com/samhsu-dev/static-php-py
Project-URL: Repository, https://github.com/samhsu-dev/static-php-py
Project-URL: Issues, https://github.com/samhsu-dev/static-php-py/issues
Author: static-php-py contributors
License:                     GNU GENERAL PUBLIC LICENSE
License-File: LICENSE
Keywords: binary,php,static-php-cli,wrapper
Classifier: Development Status :: 3 - Alpha
Classifier: Intended Audience :: Developers
Classifier: License :: OSI Approved :: Apache Software License
Classifier: Programming Language :: Python :: 3
Classifier: Programming Language :: Python :: 3.9
Classifier: Programming Language :: Python :: 3.10
Classifier: Programming Language :: Python :: 3.11
Classifier: Programming Language :: Python :: 3.12
Classifier: Topic :: Software Development :: Libraries :: Python Modules
Requires-Python: >=3.9
Requires-Dist: platformdirs>=4.0.0
